{
  "rules": {
    "driver_locations": {
      // Anyone can read live driver locations (public transport tracking)
      ".read": true,
      // Index routeId so orderByChild('routeId') queries are efficient
      ".indexOn": ["routeId"],
      "$driverId": {
        ".write": true,
        ".validate": "newData.hasChildren(['lat','lng','routeId','isActive','updatedAt'])"
      }
    },
    // Deny all other paths by default
    "$other": {
      ".read": false,
      ".write": false
    }
  }
}
